maxcube/__init__.py
maxcube/buffer.py
maxcube/commander.py
maxcube/connection.py
maxcube/cube.py
maxcube/deadline.py
maxcube/device.py
maxcube/message.py
maxcube/room.py
maxcube/thermostat.py
maxcube/wallthermostat.py
maxcube/windowshutter.py
maxcube_api-0.4.2.dist-info/LICENSE
maxcube_api-0.4.2.dist-info/METADATA
maxcube_api-0.4.2.dist-info/WHEEL
maxcube_api-0.4.2.dist-info/top_level.txt
maxcube_api-0.4.2.dist-info/RECORD
