Metadata-Version: 2.1
Name: maxcube-api
Version: 0.4.2
Summary: eQ-3/ELV MAX! Cube Python API
Home-page: https://github.com/hackercowboy/python-maxcube-api.git
Author: David Uebelacker
Author-email: david@uebelacker.ch
License: Type license() to see the full license text
Platform: UNKNOWN
Requires-Python: >=3.7
